{
  "signals": {
    "connections": [
      {
        "object": "timer",
        "signal": "timeout",
        "slot": "call_func",
        "file": "MdHelpers.py"
      },
      {
        "object": "gDatabase",
        "signal": "unknown",
        "slot": "",
        "file": "MdModel.py"
      },
      {
        "object": "gDatabase",
        "signal": "unknown",
        "slot": "",
        "file": "migrate.py"
      },
      {
        "object": "self.actionNewDataset",
        "signal": "triggered",
        "slot": "self.on_action_new_dataset_triggered",
        "file": "Modan2.py"
      },
      {
        "object": "self.actionCellSelection",
        "signal": "triggered",
        "slot": "self.on_action_cell_selection_triggered",
        "file": "Modan2.py"
      },
      {
        "object": "self.actionRowSelection",
        "signal": "triggered",
        "slot": "self.on_action_row_selection_triggered",
        "file": "Modan2.py"
      },
      {
        "object": "self.actionAddVariable",
        "signal": "triggered",
        "slot": "self.on_action_add_variable_triggered",
        "file": "Modan2.py"
      },
      {
        "object": "self.actionSaveChanges",
        "signal": "triggered",
        "slot": "self.on_btnSaveChanges_clicked",
        "file": "Modan2.py"
      },
      {
        "object": "self.actionNewObject",
        "signal": "triggered",
        "slot": "self.on_action_new_object_triggered",
        "file": "Modan2.py"
      },
      {
        "object": "self.actionEditObject",
        "signal": "triggered",
        "slot": "self.on_tableView_doubleClicked",
        "file": "Modan2.py"
      },
      {
        "object": "self.actionImport",
        "signal": "triggered",
        "slot": "self.on_action_import_dataset_triggered",
        "file": "Modan2.py"
      },
      {
        "object": "self.actionExport",
        "signal": "triggered",
        "slot": "self.on_action_export_dataset_triggered",
        "file": "Modan2.py"
      },
      {
        "object": "self.actionAnalyze",
        "signal": "triggered",
        "slot": "self.on_action_analyze_dataset_triggered",
        "file": "Modan2.py"
      },
      {
        "object": "self.actionPreferences",
        "signal": "triggered",
        "slot": "self.on_action_edit_preferences_triggered",
        "file": "Modan2.py"
      },
      {
        "object": "self.actionExit",
        "signal": "triggered",
        "slot": "self.on_action_exit_triggered",
        "file": "Modan2.py"
      },
      {
        "object": "self.actionAbout",
        "signal": "triggered",
        "slot": "self.on_action_about_triggered",
        "file": "Modan2.py"
      },
      {
        "object": "self.actionTogglePreview",
        "signal": "triggered",
        "slot": "self.toggle_object_overlay_auto_show",
        "file": "Modan2.py"
      },
      {
        "object": "self.controller",
        "signal": "dataset_created",
        "slot": "self.on_dataset_created",
        "file": "Modan2.py"
      },
      {
        "object": "self.controller",
        "signal": "dataset_updated",
        "slot": "self.on_dataset_updated",
        "file": "Modan2.py"
      },
      {
        "object": "self.controller",
        "signal": "object_added",
        "slot": "self.on_object_added",
        "file": "Modan2.py"
      },
      {
        "object": "self.controller",
        "signal": "object_updated",
        "slot": "self.on_object_updated",
        "file": "Modan2.py"
      },
      {
        "object": "self.controller",
        "signal": "analysis_completed",
        "slot": "self.on_analysis_completed",
        "file": "Modan2.py"
      },
      {
        "object": "self.controller",
        "signal": "analysis_failed",
        "slot": "self.on_analysis_failed",
        "file": "Modan2.py"
      },
      {
        "object": "self.controller",
        "signal": "error_occurred",
        "slot": "self.on_controller_error",
        "file": "Modan2.py"
      },
      {
        "object": "self.btnSaveChanges",
        "signal": "clicked",
        "slot": "self.on_btnSaveChanges_clicked",
        "file": "Modan2.py"
      },
      {
        "object": "self.btnAddObject",
        "signal": "clicked",
        "slot": "self.on_action_new_object_triggered",
        "file": "Modan2.py"
      },
      {
        "object": "self.btnEditObject",
        "signal": "clicked",
        "slot": "self.on_tableView_doubleClicked",
        "file": "Modan2.py"
      },
      {
        "object": "self.btnAddProperty",
        "signal": "clicked",
        "slot": "self.on_action_add_variable_triggered",
        "file": "Modan2.py"
      },
      {
        "object": "self.overlay_toggle_button",
        "signal": "clicked",
        "slot": "self.toggle_object_overlay_auto_show",
        "file": "Modan2.py"
      },
      {
        "object": "self.btnSaveAnalysis",
        "signal": "clicked",
        "slot": "self.btnSaveAnalysis_clicked",
        "file": "Modan2.py"
      },
      {
        "object": "self.btnAnalysisDetail",
        "signal": "clicked",
        "slot": "self.btnAnalysisDetail_clicked",
        "file": "Modan2.py"
      },
      {
        "object": "self.btnDataExploration",
        "signal": "clicked",
        "slot": "self.btnDataExploration_clicked",
        "file": "Modan2.py"
      },
      {
        "object": "self.treeView",
        "signal": "doubleClicked",
        "slot": "self.on_treeView_doubleClicked",
        "file": "Modan2.py"
      },
      {
        "object": "self.tableView",
        "signal": "doubleClicked",
        "slot": "self.on_tableView_doubleClicked",
        "file": "Modan2.py"
      },
      {
        "object": "self.treeView",
        "signal": "customContextMenuRequested",
        "slot": "self.open_treeview_menu",
        "file": "Modan2.py"
      },
      {
        "object": "self.dataset_selection_model",
        "signal": "selectionChanged",
        "slot": "self.on_dataset_selection_changed",
        "file": "Modan2.py"
      },
      {
        "object": "self.object_model",
        "signal": "dataChangedCustomSignal",
        "slot": "self.on_object_data_changed",
        "file": "Modan2.py"
      },
      {
        "object": "self.object_selection_model",
        "signal": "selectionChanged",
        "slot": "self.on_object_selection_changed",
        "file": "Modan2.py"
      },
      {
        "object": "action_add_dataset",
        "signal": "triggered",
        "slot": "self.on_action_new_dataset_triggered",
        "file": "Modan2.py"
      },
      {
        "object": "action_add_object",
        "signal": "triggered",
        "slot": "self.on_action_new_object_triggered",
        "file": "Modan2.py"
      },
      {
        "object": "action_add_analysis",
        "signal": "triggered",
        "slot": "self.on_action_analyze_dataset_triggered",
        "file": "Modan2.py"
      },
      {
        "object": "action_explore_data",
        "signal": "triggered",
        "slot": "self.on_action_explore_data_triggered",
        "file": "Modan2.py"
      },
      {
        "object": "action_delete_analysis",
        "signal": "triggered",
        "slot": "self.on_action_delete_analysis_triggered",
        "file": "Modan2.py"
      },
      {
        "object": "action_refresh_tree",
        "signal": "triggered",
        "slot": "self.load_dataset",
        "file": "Modan2.py"
      },
      {
        "object": "self.treeView.selectionModel(\u2026)",
        "signal": "selectionChanged",
        "slot": "self.on_dataset_selection_changed",
        "file": "Modan2.py"
      },
      {
        "object": "self",
        "signal": "itemSelectionChanged",
        "slot": "self._on_selection_changed",
        "file": "ModanWidgets.py"
      },
      {
        "object": "self",
        "signal": "customContextMenuRequested",
        "slot": "self._show_context_menu",
        "file": "ModanWidgets.py"
      },
      {
        "object": "self",
        "signal": "itemDoubleClicked",
        "slot": "self._on_item_double_clicked",
        "file": "ModanWidgets.py"
      },
      {
        "object": "self",
        "signal": "itemSelectionChanged",
        "slot": "self._on_selection_changed",
        "file": "ModanWidgets.py"
      },
      {
        "object": "self",
        "signal": "customContextMenuRequested",
        "slot": "self._show_context_menu",
        "file": "ModanWidgets.py"
      },
      {
        "object": "self",
        "signal": "cellDoubleClicked",
        "slot": "self._on_cell_double_clicked",
        "file": "ModanWidgets.py"
      },
      {
        "object": "self.edtAnalysisName",
        "signal": "textChanged",
        "slot": "self.edtAnalysisName_changed",
        "file": "analysis_dialog.py"
      },
      {
        "object": "self.btnOK",
        "signal": "clicked",
        "slot": "self.btnOK_clicked",
        "file": "analysis_dialog.py"
      },
      {
        "object": "self.btnCancel",
        "signal": "clicked",
        "slot": "self.btnCancel_clicked",
        "file": "analysis_dialog.py"
      },
      {
        "object": "self.controller",
        "signal": "analysis_progress",
        "slot": "self.on_analysis_progress",
        "file": "analysis_dialog.py"
      },
      {
        "object": "self.controller",
        "signal": "analysis_completed",
        "slot": "self.on_analysis_completed",
        "file": "analysis_dialog.py"
      },
      {
        "object": "self.controller",
        "signal": "analysis_failed",
        "slot": "self.on_analysis_failed",
        "file": "analysis_dialog.py"
      },
      {
        "object": "self.btn_ok",
        "signal": "clicked",
        "slot": "self.accept",
        "file": "base_dialog.py"
      },
      {
        "object": "self.btn_cancel",
        "signal": "clicked",
        "slot": "self.reject",
        "file": "base_dialog.py"
      },
      {
        "object": "self.btnOK",
        "signal": "clicked",
        "slot": "self.btnOK_clicked",
        "file": "calibration_dialog.py"
      },
      {
        "object": "self.btnCancel",
        "signal": "clicked",
        "slot": "self.btnCancel_clicked",
        "file": "calibration_dialog.py"
      },
      {
        "object": "self.cbxShowIndex",
        "signal": "stateChanged",
        "slot": "self.show_index_state_changed",
        "file": "dataset_analysis_dialog.py"
      },
      {
        "object": "self.cbxShowWireframe",
        "signal": "stateChanged",
        "slot": "self.show_wireframe_state_changed",
        "file": "dataset_analysis_dialog.py"
      },
      {
        "object": "self.cbxShowBaseline",
        "signal": "stateChanged",
        "slot": "self.show_baseline_state_changed",
        "file": "dataset_analysis_dialog.py"
      },
      {
        "object": "self.cbxShowAverage",
        "signal": "stateChanged",
        "slot": "self.show_average_state_changed",
        "file": "dataset_analysis_dialog.py"
      },
      {
        "object": "self.cbxAutoRotate",
        "signal": "stateChanged",
        "slot": "self.auto_rotate_state_changed",
        "file": "dataset_analysis_dialog.py"
      },
      {
        "object": "self.btnSelectAll",
        "signal": "clicked",
        "slot": "self.select_all",
        "file": "dataset_analysis_dialog.py"
      },
      {
        "object": "self.btnSelectNone",
        "signal": "clicked",
        "slot": "self.select_none",
        "file": "dataset_analysis_dialog.py"
      },
      {
        "object": "self.btnSelectInvert",
        "signal": "clicked",
        "slot": "self.select_invert",
        "file": "dataset_analysis_dialog.py"
      },
      {
        "object": "self.cbxFlipAxis1",
        "signal": "stateChanged",
        "slot": "self.flip_axis_changed",
        "file": "dataset_analysis_dialog.py"
      },
      {
        "object": "self.cbxFlipAxis2",
        "signal": "stateChanged",
        "slot": "self.flip_axis_changed",
        "file": "dataset_analysis_dialog.py"
      },
      {
        "object": "self.cbxFlipAxis3",
        "signal": "stateChanged",
        "slot": "self.flip_axis_changed",
        "file": "dataset_analysis_dialog.py"
      },
      {
        "object": "self.rb2DChartDim",
        "signal": "toggled",
        "slot": "self.on_chart_dim_changed",
        "file": "dataset_analysis_dialog.py"
      },
      {
        "object": "self.rb3DChartDim",
        "signal": "toggled",
        "slot": "self.on_chart_dim_changed",
        "file": "dataset_analysis_dialog.py"
      },
      {
        "object": "self.cbxDepthShade",
        "signal": "toggled",
        "slot": "self.on_chart_dim_changed",
        "file": "dataset_analysis_dialog.py"
      },
      {
        "object": "self.cbxLegend",
        "signal": "toggled",
        "slot": "self.on_chart_dim_changed",
        "file": "dataset_analysis_dialog.py"
      },
      {
        "object": "self.cbxAxisLabel",
        "signal": "toggled",
        "slot": "self.on_chart_dim_changed",
        "file": "dataset_analysis_dialog.py"
      },
      {
        "object": "self.comboPropertyName",
        "signal": "currentIndexChanged",
        "slot": "self.propertyname_changed",
        "file": "dataset_analysis_dialog.py"
      },
      {
        "object": "self.btnChartOptions",
        "signal": "clicked",
        "slot": "self.chart_options_clicked",
        "file": "dataset_analysis_dialog.py"
      },
      {
        "object": "self.comboAxis1",
        "signal": "currentIndexChanged",
        "slot": "self.axis_changed",
        "file": "dataset_analysis_dialog.py"
      },
      {
        "object": "self.comboAxis2",
        "signal": "currentIndexChanged",
        "slot": "self.axis_changed",
        "file": "dataset_analysis_dialog.py"
      },
      {
        "object": "self.comboAxis3",
        "signal": "currentIndexChanged",
        "slot": "self.axis_changed",
        "file": "dataset_analysis_dialog.py"
      },
      {
        "object": "self.btnSuperimpose",
        "signal": "clicked",
        "slot": "self.on_btnSuperimpose_clicked",
        "file": "dataset_analysis_dialog.py"
      },
      {
        "object": "self.rbPCA",
        "signal": "toggled",
        "slot": "self.on_analysis_type_changed",
        "file": "dataset_analysis_dialog.py"
      },
      {
        "object": "self.rbCVA",
        "signal": "toggled",
        "slot": "self.on_analysis_type_changed",
        "file": "dataset_analysis_dialog.py"
      },
      {
        "object": "self.btnAnalyze",
        "signal": "clicked",
        "slot": "self.on_btn_analysis_clicked",
        "file": "dataset_analysis_dialog.py"
      },
      {
        "object": "self.btnSaveResults",
        "signal": "clicked",
        "slot": "self.on_btnSaveResults_clicked",
        "file": "dataset_analysis_dialog.py"
      },
      {
        "object": "self.comboPropertyName",
        "signal": "currentIndexChanged",
        "slot": "self.propertyname_changed",
        "file": "dataset_analysis_dialog.py"
      },
      {
        "object": "self.object_selection_model",
        "signal": "selectionChanged",
        "slot": "self.on_object_selection_changed",
        "file": "dataset_analysis_dialog.py"
      },
      {
        "object": "close_shortcut",
        "signal": "activated",
        "slot": "self.close",
        "file": "dataset_dialog.py"
      },
      {
        "object": "self.btnAddVariable",
        "signal": "clicked",
        "slot": "self.addVariable",
        "file": "dataset_dialog.py"
      },
      {
        "object": "self.btnDeleteVariable",
        "signal": "clicked",
        "slot": "self.deleteVariable",
        "file": "dataset_dialog.py"
      },
      {
        "object": "self.btnMoveUp",
        "signal": "clicked",
        "slot": "self.moveUp",
        "file": "dataset_dialog.py"
      },
      {
        "object": "self.btnMoveDown",
        "signal": "clicked",
        "slot": "self.moveDown",
        "file": "dataset_dialog.py"
      },
      {
        "object": "self.btnOkay",
        "signal": "clicked",
        "slot": "self.Okay",
        "file": "dataset_dialog.py"
      },
      {
        "object": "self.btnDelete",
        "signal": "clicked",
        "slot": "self.Delete",
        "file": "dataset_dialog.py"
      },
      {
        "object": "self.btnCancel",
        "signal": "clicked",
        "slot": "self.Cancel",
        "file": "dataset_dialog.py"
      },
      {
        "object": "close_shortcut",
        "signal": "activated",
        "slot": "self.close",
        "file": "data_exploration_dialog.py"
      },
      {
        "object": "self.comboVisualization",
        "signal": "currentIndexChanged",
        "slot": "self.comboVisualizationMethod_changed",
        "file": "data_exploration_dialog.py"
      },
      {
        "object": "self.comboGroupBy",
        "signal": "currentIndexChanged",
        "slot": "self.comboGroupBy_changed",
        "file": "data_exploration_dialog.py"
      },
      {
        "object": "self.rb2DChartDim",
        "signal": "toggled",
        "slot": "self.on_chart_dim_changed",
        "file": "data_exploration_dialog.py"
      },
      {
        "object": "self.rb3DChartDim",
        "signal": "toggled",
        "slot": "self.on_chart_dim_changed",
        "file": "data_exploration_dialog.py"
      },
      {
        "object": "self.cbxLegend",
        "signal": "toggled",
        "slot": "self.update_chart",
        "file": "data_exploration_dialog.py"
      },
      {
        "object": "self.cbxShowVariance",
        "signal": "toggled",
        "slot": "self.update_chart",
        "file": "data_exploration_dialog.py"
      },
      {
        "object": "self.cbxDataPointLabels",
        "signal": "toggled",
        "slot": "self.update_chart",
        "file": "data_exploration_dialog.py"
      },
      {
        "object": "self.cbxFlipAxis1",
        "signal": "stateChanged",
        "slot": "self.flip_axis_changed",
        "file": "data_exploration_dialog.py"
      },
      {
        "object": "self.cbxFlipAxis2",
        "signal": "stateChanged",
        "slot": "self.flip_axis_changed",
        "file": "data_exploration_dialog.py"
      },
      {
        "object": "self.cbxFlipAxis3",
        "signal": "stateChanged",
        "slot": "self.flip_axis_changed",
        "file": "data_exploration_dialog.py"
      },
      {
        "object": "self.comboAxis1",
        "signal": "currentIndexChanged",
        "slot": "self.axis_changed",
        "file": "data_exploration_dialog.py"
      },
      {
        "object": "self.comboAxis2",
        "signal": "currentIndexChanged",
        "slot": "self.axis_changed",
        "file": "data_exploration_dialog.py"
      },
      {
        "object": "self.comboAxis3",
        "signal": "currentIndexChanged",
        "slot": "self.axis_changed",
        "file": "data_exploration_dialog.py"
      },
      {
        "object": "self.cbxDepthShade",
        "signal": "toggled",
        "slot": "self.update_chart",
        "file": "data_exploration_dialog.py"
      },
      {
        "object": "self.cbxAverage",
        "signal": "stateChanged",
        "slot": "self.update_chart",
        "file": "data_exploration_dialog.py"
      },
      {
        "object": "self.cbxConvexHull",
        "signal": "stateChanged",
        "slot": "self.update_chart",
        "file": "data_exploration_dialog.py"
      },
      {
        "object": "self.cbxConfidenceEllipse",
        "signal": "stateChanged",
        "slot": "self.update_chart",
        "file": "data_exploration_dialog.py"
      },
      {
        "object": "self.cbxShapeGrid",
        "signal": "stateChanged",
        "slot": "self.cbxShapeGrid_state_changed",
        "file": "data_exploration_dialog.py"
      },
      {
        "object": "self.cbxArrow",
        "signal": "stateChanged",
        "slot": "self.arrow_preference_changed",
        "file": "data_exploration_dialog.py"
      },
      {
        "object": "self.btnArrowColor",
        "signal": "clicked",
        "slot": "self.on_btnArrowColor_clicked",
        "file": "data_exploration_dialog.py"
      },
      {
        "object": "self.sgpWidget",
        "signal": "shape_preference_changed",
        "slot": "self.shape_grid_preference_changed",
        "file": "data_exploration_dialog.py"
      },
      {
        "object": "self.cbxRegression",
        "signal": "stateChanged",
        "slot": "self.update_chart",
        "file": "data_exploration_dialog.py"
      },
      {
        "object": "self.comboRegressionBasedOn",
        "signal": "currentIndexChanged",
        "slot": "self.comboRegressionBasedOn_changed",
        "file": "data_exploration_dialog.py"
      },
      {
        "object": "self.comboRegressionBy",
        "signal": "currentIndexChanged",
        "slot": "self.comboRegressionBy_changed",
        "file": "data_exploration_dialog.py"
      },
      {
        "object": "self.comboSelectGroup",
        "signal": "currentIndexChanged",
        "slot": "self.comboSelectGroup_changed",
        "file": "data_exploration_dialog.py"
      },
      {
        "object": "model",
        "signal": "itemChanged",
        "slot": "self.comboSelectGroup_itemChanged",
        "file": "data_exploration_dialog.py"
      },
      {
        "object": "self.cbxExtrapolate",
        "signal": "stateChanged",
        "slot": "self.update_chart",
        "file": "data_exploration_dialog.py"
      },
      {
        "object": "self.sbxDegree",
        "signal": "textChanged",
        "slot": "self.update_chart",
        "file": "data_exploration_dialog.py"
      },
      {
        "object": "self.cbxAnnotation",
        "signal": "stateChanged",
        "slot": "self.update_chart",
        "file": "data_exploration_dialog.py"
      },
      {
        "object": "self.plot_preference_button",
        "signal": "clicked",
        "slot": "self.show_plot_preference",
        "file": "data_exploration_dialog.py"
      },
      {
        "object": "self.btn_save_plot",
        "signal": "clicked",
        "slot": "self.export_chart",
        "file": "data_exploration_dialog.py"
      },
      {
        "object": "self.btnResetPose",
        "signal": "clicked",
        "slot": "self.reset_shape_pose",
        "file": "data_exploration_dialog.py"
      },
      {
        "object": "self.btnAnimate",
        "signal": "clicked",
        "slot": "self.animate_shape",
        "file": "data_exploration_dialog.py"
      },
      {
        "object": "self.cbxRecordAnimation",
        "signal": "stateChanged",
        "slot": "self.record_animation_changed",
        "file": "data_exploration_dialog.py"
      },
      {
        "object": "self.shape_preference_button",
        "signal": "clicked",
        "slot": "self.shape_preference_button_clicked",
        "file": "data_exploration_dialog.py"
      },
      {
        "object": "self.visualization_splitter",
        "signal": "splitterMoved",
        "slot": "self.on_splitter_moved",
        "file": "data_exploration_dialog.py"
      },
      {
        "object": "self.timer",
        "signal": "timeout",
        "slot": "self.chart_animation",
        "file": "data_exploration_dialog.py"
      },
      {
        "object": "shape_button",
        "signal": "clicked",
        "slot": "lambda",
        "file": "data_exploration_dialog.py"
      },
      {
        "object": "shape_preference",
        "signal": "shape_preference_changed",
        "slot": "self.shape_preference_changed",
        "file": "data_exploration_dialog.py"
      },
      {
        "object": "shape_preference",
        "signal": "shape_preference_changed",
        "slot": "self.shape_preference_changed",
        "file": "data_exploration_dialog.py"
      },
      {
        "object": "self.btnExport",
        "signal": "clicked",
        "slot": "self.export_dataset",
        "file": "export_dialog.py"
      },
      {
        "object": "self.btnCancel",
        "signal": "clicked",
        "slot": "self.close",
        "file": "export_dialog.py"
      },
      {
        "object": "self.btnMoveRight",
        "signal": "clicked",
        "slot": "self.move_right",
        "file": "export_dialog.py"
      },
      {
        "object": "self.btnMoveLeft",
        "signal": "clicked",
        "slot": "self.move_left",
        "file": "export_dialog.py"
      },
      {
        "object": "self.rbTPS",
        "signal": "clicked",
        "slot": "self.on_rbTPS_clicked",
        "file": "export_dialog.py"
      },
      {
        "object": "self.rbX1Y1",
        "signal": "clicked",
        "slot": "self.on_rbX1Y1_clicked",
        "file": "export_dialog.py"
      },
      {
        "object": "self.rbMorphologika",
        "signal": "clicked",
        "slot": "self.on_rbMorphologika_clicked",
        "file": "export_dialog.py"
      },
      {
        "object": "self.rbJSONZip",
        "signal": "clicked",
        "slot": "self.on_rbJSONZip_clicked",
        "file": "export_dialog.py"
      },
      {
        "object": "self.chkIncludeFiles",
        "signal": "toggled",
        "slot": "self.update_estimated_size",
        "file": "export_dialog.py"
      },
      {
        "object": "self.rbProcrustes",
        "signal": "clicked",
        "slot": "self.on_rbProcrustes_clicked",
        "file": "export_dialog.py"
      },
      {
        "object": "self.rbBookstein",
        "signal": "clicked",
        "slot": "self.on_rbBookstein_clicked",
        "file": "export_dialog.py"
      },
      {
        "object": "self.rbRFTRA",
        "signal": "clicked",
        "slot": "self.on_rbRFTRA_clicked",
        "file": "export_dialog.py"
      },
      {
        "object": "self.rbNone",
        "signal": "clicked",
        "slot": "self.on_rbNone_clicked",
        "file": "export_dialog.py"
      },
      {
        "object": "self.btnOpenFile",
        "signal": "clicked",
        "slot": "self.open_file",
        "file": "import_dialog.py"
      },
      {
        "object": "self.chkFileType",
        "signal": "buttonClicked",
        "slot": "self.file_type_changed",
        "file": "import_dialog.py"
      },
      {
        "object": "self.btnImport",
        "signal": "clicked",
        "slot": "self.import_file",
        "file": "import_dialog.py"
      },
      {
        "object": "close_shortcut",
        "signal": "activated",
        "slot": "self.close",
        "file": "object_dialog.py"
      },
      {
        "object": "self.btnAddMissing",
        "signal": "clicked",
        "slot": "self.btnAddMissing_clicked",
        "file": "object_dialog.py"
      },
      {
        "object": "self.cbxShowIndex",
        "signal": "stateChanged",
        "slot": "self.show_index_state_changed",
        "file": "object_dialog.py"
      },
      {
        "object": "self.cbxShowWireframe",
        "signal": "stateChanged",
        "slot": "self.show_wireframe_state_changed",
        "file": "object_dialog.py"
      },
      {
        "object": "self.cbxShowPolygon",
        "signal": "stateChanged",
        "slot": "self.show_polygon_state_changed",
        "file": "object_dialog.py"
      },
      {
        "object": "self.cbxShowBaseline",
        "signal": "stateChanged",
        "slot": "self.show_baseline_state_changed",
        "file": "object_dialog.py"
      },
      {
        "object": "self.cbxAutoRotate",
        "signal": "stateChanged",
        "slot": "self.auto_rotate_state_changed",
        "file": "object_dialog.py"
      },
      {
        "object": "self.cbxShowModel",
        "signal": "stateChanged",
        "slot": "self.show_model_state_changed",
        "file": "object_dialog.py"
      },
      {
        "object": "self.inputX",
        "signal": "returnPressed",
        "slot": "self.input_coords_process",
        "file": "object_dialog.py"
      },
      {
        "object": "self.inputY",
        "signal": "returnPressed",
        "slot": "self.input_coords_process",
        "file": "object_dialog.py"
      },
      {
        "object": "self.inputZ",
        "signal": "returnPressed",
        "slot": "self.input_coords_process",
        "file": "object_dialog.py"
      },
      {
        "object": "Subscript",
        "signal": "unknown",
        "slot": "self.x_changed",
        "file": "object_dialog.py"
      },
      {
        "object": "self.btnAddInput",
        "signal": "clicked",
        "slot": "self.btnAddInput_clicked",
        "file": "object_dialog.py"
      },
      {
        "object": "self.btnUpdateInput",
        "signal": "clicked",
        "slot": "self.btnUpdateInput_clicked",
        "file": "object_dialog.py"
      },
      {
        "object": "self.btnDeleteInput",
        "signal": "clicked",
        "slot": "self.btnDeleteInput_clicked",
        "file": "object_dialog.py"
      },
      {
        "object": "self.btnLandmark",
        "signal": "clicked",
        "slot": "self.btnLandmark_clicked",
        "file": "object_dialog.py"
      },
      {
        "object": "self.btnWireframe",
        "signal": "clicked",
        "slot": "self.btnWireframe_clicked",
        "file": "object_dialog.py"
      },
      {
        "object": "self.btnCalibration",
        "signal": "clicked",
        "slot": "self.btnCalibration_clicked",
        "file": "object_dialog.py"
      },
      {
        "object": "self.cbxShowEstimated",
        "signal": "stateChanged",
        "slot": "self.toggle_estimation",
        "file": "object_dialog.py"
      },
      {
        "object": "self.btnAddFile",
        "signal": "clicked",
        "slot": "self.btnAddFile_clicked",
        "file": "object_dialog.py"
      },
      {
        "object": "self.cbxUseOriginal",
        "signal": "stateChanged",
        "slot": "self.cbxUseOriginal_state_changed",
        "file": "object_dialog.py"
      },
      {
        "object": "self.btnPrevious",
        "signal": "clicked",
        "slot": "self.Previous",
        "file": "object_dialog.py"
      },
      {
        "object": "self.btnNext",
        "signal": "clicked",
        "slot": "self.Next",
        "file": "object_dialog.py"
      },
      {
        "object": "self.btnOkay",
        "signal": "clicked",
        "slot": "self.Okay",
        "file": "object_dialog.py"
      },
      {
        "object": "self.btnDelete",
        "signal": "clicked",
        "slot": "self.Delete",
        "file": "object_dialog.py"
      },
      {
        "object": "self.btnCancel",
        "signal": "clicked",
        "slot": "self.Cancel",
        "file": "object_dialog.py"
      },
      {
        "object": "self.edtLandmarkStr",
        "signal": "itemSelectionChanged",
        "slot": "self.on_landmark_selected",
        "file": "object_dialog.py"
      },
      {
        "object": "self.edtLandmarkStr",
        "signal": "itemChanged",
        "slot": "self.on_landmark_cell_changed",
        "file": "object_dialog.py"
      },
      {
        "object": "self.rbRememberGeometryYes",
        "signal": "clicked",
        "slot": "self.on_rbRememberGeometryYes_clicked",
        "file": "preferences_dialog.py"
      },
      {
        "object": "self.rbRememberGeometryNo",
        "signal": "clicked",
        "slot": "self.on_rbRememberGeometryNo_clicked",
        "file": "preferences_dialog.py"
      },
      {
        "object": "self.rbToolbarIconLarge",
        "signal": "clicked",
        "slot": "self.on_rbToolbarIconLarge_clicked",
        "file": "preferences_dialog.py"
      },
      {
        "object": "self.rbToolbarIconSmall",
        "signal": "clicked",
        "slot": "self.on_rbToolbarIconSmall_clicked",
        "file": "preferences_dialog.py"
      },
      {
        "object": "self.rbToolbarIconMedium",
        "signal": "clicked",
        "slot": "self.on_rbToolbarIconMedium_clicked",
        "file": "preferences_dialog.py"
      },
      {
        "object": "self.rbPlotLarge",
        "signal": "clicked",
        "slot": "self.on_rbPlotLarge_clicked",
        "file": "preferences_dialog.py"
      },
      {
        "object": "self.rbPlotSmall",
        "signal": "clicked",
        "slot": "self.on_rbPlotSmall_clicked",
        "file": "preferences_dialog.py"
      },
      {
        "object": "self.rbPlotMedium",
        "signal": "clicked",
        "slot": "self.on_rbPlotMedium_clicked",
        "file": "preferences_dialog.py"
      },
      {
        "object": "self.btnResetMarkers",
        "signal": "clicked",
        "slot": "self.on_btnResetMarkers_clicked",
        "file": "preferences_dialog.py"
      },
      {
        "object": "self.btnResetVivid",
        "signal": "clicked",
        "slot": "self.on_btnResetVivid_clicked",
        "file": "preferences_dialog.py"
      },
      {
        "object": "self.btnResetPastel",
        "signal": "clicked",
        "slot": "self.on_btnResetPastel_clicked",
        "file": "preferences_dialog.py"
      },
      {
        "object": "self.combo2DLandmarkSize",
        "signal": "currentIndexChanged",
        "slot": "lambda",
        "file": "preferences_dialog.py"
      },
      {
        "object": "self.combo3DLandmarkSize",
        "signal": "currentIndexChanged",
        "slot": "lambda",
        "file": "preferences_dialog.py"
      },
      {
        "object": "self.combo2DWireframeThickness",
        "signal": "currentIndexChanged",
        "slot": "lambda",
        "file": "preferences_dialog.py"
      },
      {
        "object": "self.combo3DWireframeThickness",
        "signal": "currentIndexChanged",
        "slot": "lambda",
        "file": "preferences_dialog.py"
      },
      {
        "object": "self.combo2DIndexSize",
        "signal": "currentIndexChanged",
        "slot": "lambda",
        "file": "preferences_dialog.py"
      },
      {
        "object": "self.combo3DIndexSize",
        "signal": "currentIndexChanged",
        "slot": "lambda",
        "file": "preferences_dialog.py"
      },
      {
        "object": "self.comboLang",
        "signal": "currentIndexChanged",
        "slot": "self.comboLangIndexChanged",
        "file": "preferences_dialog.py"
      },
      {
        "object": "self.btnOkay",
        "signal": "clicked",
        "slot": "self.Okay",
        "file": "preferences_dialog.py"
      },
      {
        "object": "self.btnCancel",
        "signal": "clicked",
        "slot": "self.Cancel",
        "file": "preferences_dialog.py"
      },
      {
        "object": "combo",
        "signal": "currentIndexChanged",
        "slot": "lambda",
        "file": "preferences_dialog.py"
      },
      {
        "object": "self.btnStop",
        "signal": "clicked",
        "slot": "self.set_stop_progress",
        "file": "progress_dialog.py"
      },
      {
        "object": "drag",
        "signal": "actionChanged",
        "slot": "update_cursor",
        "file": "drag_test2.py"
      },
      {
        "object": "self.timer",
        "signal": "timeout",
        "slot": "self.check_modifiers",
        "file": "drag_test6.py"
      },
      {
        "object": "self.timer",
        "signal": "timeout",
        "slot": "self.check_modifiers",
        "file": "drag_test7.py"
      },
      {
        "object": "test_db",
        "signal": "unknown",
        "slot": "",
        "file": "conftest.py"
      },
      {
        "object": "timer",
        "signal": "timeout",
        "slot": "auto_click_messagebox",
        "file": "test_analysis_workflow.py"
      },
      {
        "object": "timer",
        "signal": "timeout",
        "slot": "auto_click_messagebox",
        "file": "test_analysis_workflow.py"
      },
      {
        "object": "timer",
        "signal": "timeout",
        "slot": "auto_click_messagebox",
        "file": "test_import.py"
      },
      {
        "object": "table",
        "signal": "itemChanged",
        "slot": "dlg.on_landmark_cell_changed",
        "file": "test_landmark_cell_validation.py"
      },
      {
        "object": "test_db",
        "signal": "unknown",
        "slot": "",
        "file": "test_mdmodel.py"
      },
      {
        "object": "widget",
        "signal": "shape_preference_changed",
        "slot": "mock_slot",
        "file": "test_shape_preference.py"
      },
      {
        "object": "widget",
        "signal": "shape_preference_changed",
        "slot": "mock_slot",
        "file": "test_shape_preference.py"
      },
      {
        "object": "button",
        "signal": "clicked",
        "slot": "on_clicked",
        "file": "test_widgets.py"
      },
      {
        "object": "self.timer",
        "signal": "timeout",
        "slot": "self.timeout",
        "file": "object_viewer_3d.py"
      },
      {
        "object": "self.analysis_tab",
        "signal": "currentChanged",
        "slot": "self.on_tab_changed",
        "file": "analysis_info.py"
      },
      {
        "object": "self.comboPcaGroupBy",
        "signal": "currentIndexChanged",
        "slot": "self.comboPcaGroupBy_changed",
        "file": "analysis_info.py"
      },
      {
        "object": "self.comboCvaGroupBy",
        "signal": "currentIndexChanged",
        "slot": "self.comboCvaGroupBy_changed",
        "file": "analysis_info.py"
      },
      {
        "object": "self.comboManovaGroupBy",
        "signal": "currentIndexChanged",
        "slot": "self.comboManovaGroupBy_changed",
        "file": "analysis_info.py"
      },
      {
        "object": "self",
        "signal": "pressed",
        "slot": "self.update",
        "file": "pic_button.py"
      },
      {
        "object": "self",
        "signal": "released",
        "slot": "self.update",
        "file": "pic_button.py"
      },
      {
        "object": "self.btnLMColor",
        "signal": "clicked",
        "slot": "self.on_btnLMColor_clicked",
        "file": "shape_preference.py"
      },
      {
        "object": "self.btnEdgeColor",
        "signal": "clicked",
        "slot": "self.on_btnEdgeColor_clicked",
        "file": "shape_preference.py"
      },
      {
        "object": "self.btnFaceColor",
        "signal": "clicked",
        "slot": "self.on_btnFaceColor_clicked",
        "file": "shape_preference.py"
      },
      {
        "object": "self.cbxShow",
        "signal": "stateChanged",
        "slot": "self.cbxShow_stateChanged",
        "file": "shape_preference.py"
      },
      {
        "object": "self.cbxShowLandmark",
        "signal": "stateChanged",
        "slot": "self.cbxShowLandmark_stateChanged",
        "file": "shape_preference.py"
      },
      {
        "object": "self.cbxShowWireframe",
        "signal": "stateChanged",
        "slot": "self.cbxShowWireframe_stateChanged",
        "file": "shape_preference.py"
      },
      {
        "object": "self.cbxShowPolygon",
        "signal": "stateChanged",
        "slot": "self.cbxShowPolygon_stateChanged",
        "file": "shape_preference.py"
      },
      {
        "object": "self.edtTitle",
        "signal": "textChanged",
        "slot": "self.edtTitle_textChanged",
        "file": "shape_preference.py"
      },
      {
        "object": "self.sliderTransparency",
        "signal": "valueChanged",
        "slot": "self.sliderTransparency_valueChanged",
        "file": "shape_preference.py"
      },
      {
        "object": "self",
        "signal": "customContextMenuRequested",
        "slot": "self.show_context_menu",
        "file": "table_view.py"
      },
      {
        "object": "self.copy_action",
        "signal": "triggered",
        "slot": "self.copy_selected_data",
        "file": "table_view.py"
      },
      {
        "object": "copy_shortcut",
        "signal": "activated",
        "slot": "self.copy_action.trigger",
        "file": "table_view.py"
      },
      {
        "object": "self.paste_action",
        "signal": "triggered",
        "slot": "self.paste_data",
        "file": "table_view.py"
      },
      {
        "object": "paste_shortcut",
        "signal": "activated",
        "slot": "self.paste_action.trigger",
        "file": "table_view.py"
      },
      {
        "object": "self.fill_sequence_action",
        "signal": "triggered",
        "slot": "self.fill_sequence",
        "file": "table_view.py"
      },
      {
        "object": "self.fill_action",
        "signal": "triggered",
        "slot": "self.fill_value",
        "file": "table_view.py"
      },
      {
        "object": "self.clear_cells_action",
        "signal": "triggered",
        "slot": "self.clear_selected_cells",
        "file": "table_view.py"
      },
      {
        "object": "self.edit_object_action",
        "signal": "triggered",
        "slot": "self.edit_selected_object",
        "file": "table_view.py"
      }
    ],
    "actions": [
      {
        "action": "self.actionNewDataset",
        "handler": "self.on_action_new_dataset_triggered",
        "file": "Modan2.py"
      },
      {
        "action": "self.actionCellSelection",
        "handler": "self.on_action_cell_selection_triggered",
        "file": "Modan2.py"
      },
      {
        "action": "self.actionRowSelection",
        "handler": "self.on_action_row_selection_triggered",
        "file": "Modan2.py"
      },
      {
        "action": "self.actionAddVariable",
        "handler": "self.on_action_add_variable_triggered",
        "file": "Modan2.py"
      },
      {
        "action": "self.actionSaveChanges",
        "handler": "self.on_btnSaveChanges_clicked",
        "file": "Modan2.py"
      },
      {
        "action": "self.actionNewObject",
        "handler": "self.on_action_new_object_triggered",
        "file": "Modan2.py"
      },
      {
        "action": "self.actionEditObject",
        "handler": "self.on_tableView_doubleClicked",
        "file": "Modan2.py"
      },
      {
        "action": "self.actionImport",
        "handler": "self.on_action_import_dataset_triggered",
        "file": "Modan2.py"
      },
      {
        "action": "self.actionExport",
        "handler": "self.on_action_export_dataset_triggered",
        "file": "Modan2.py"
      },
      {
        "action": "self.actionAnalyze",
        "handler": "self.on_action_analyze_dataset_triggered",
        "file": "Modan2.py"
      },
      {
        "action": "self.actionPreferences",
        "handler": "self.on_action_edit_preferences_triggered",
        "file": "Modan2.py"
      },
      {
        "action": "self.actionExit",
        "handler": "self.on_action_exit_triggered",
        "file": "Modan2.py"
      },
      {
        "action": "self.actionAbout",
        "handler": "self.on_action_about_triggered",
        "file": "Modan2.py"
      },
      {
        "action": "self.actionTogglePreview",
        "handler": "self.toggle_object_overlay_auto_show",
        "file": "Modan2.py"
      },
      {
        "action": "action_add_dataset",
        "handler": "self.on_action_new_dataset_triggered",
        "file": "Modan2.py"
      },
      {
        "action": "action_add_object",
        "handler": "self.on_action_new_object_triggered",
        "file": "Modan2.py"
      },
      {
        "action": "action_add_analysis",
        "handler": "self.on_action_analyze_dataset_triggered",
        "file": "Modan2.py"
      },
      {
        "action": "action_explore_data",
        "handler": "self.on_action_explore_data_triggered",
        "file": "Modan2.py"
      },
      {
        "action": "action_delete_analysis",
        "handler": "self.on_action_delete_analysis_triggered",
        "file": "Modan2.py"
      },
      {
        "action": "action_refresh_tree",
        "handler": "self.load_dataset",
        "file": "Modan2.py"
      },
      {
        "action": "self.copy_action",
        "handler": "self.copy_selected_data",
        "file": "table_view.py"
      },
      {
        "action": "self.paste_action",
        "handler": "self.paste_data",
        "file": "table_view.py"
      },
      {
        "action": "self.fill_sequence_action",
        "handler": "self.fill_sequence",
        "file": "table_view.py"
      },
      {
        "action": "self.fill_action",
        "handler": "self.fill_value",
        "file": "table_view.py"
      },
      {
        "action": "self.clear_cells_action",
        "handler": "self.clear_selected_cells",
        "file": "table_view.py"
      },
      {
        "action": "self.edit_object_action",
        "handler": "self.edit_selected_object",
        "file": "table_view.py"
      }
    ],
    "definitions": [
      {
        "name": "dataset_created",
        "signature": "object",
        "file": "ModanController.py"
      },
      {
        "name": "dataset_updated",
        "signature": "object",
        "file": "ModanController.py"
      },
      {
        "name": "dataset_deleted",
        "signature": "int",
        "file": "ModanController.py"
      },
      {
        "name": "object_added",
        "signature": "object",
        "file": "ModanController.py"
      },
      {
        "name": "object_updated",
        "signature": "object",
        "file": "ModanController.py"
      },
      {
        "name": "object_deleted",
        "signature": "int",
        "file": "ModanController.py"
      },
      {
        "name": "analysis_started",
        "signature": "str",
        "file": "ModanController.py"
      },
      {
        "name": "analysis_progress",
        "signature": "int",
        "file": "ModanController.py"
      },
      {
        "name": "analysis_completed",
        "signature": "object",
        "file": "ModanController.py"
      },
      {
        "name": "analysis_failed",
        "signature": "str",
        "file": "ModanController.py"
      },
      {
        "name": "error_occurred",
        "signature": "str",
        "file": "ModanController.py"
      },
      {
        "name": "warning_occurred",
        "signature": "str",
        "file": "ModanController.py"
      },
      {
        "name": "info_message",
        "signature": "str",
        "file": "ModanController.py"
      },
      {
        "name": "dataset_selected",
        "signature": "object",
        "file": "ModanWidgets.py"
      },
      {
        "name": "analysis_selected",
        "signature": "object",
        "file": "ModanWidgets.py"
      },
      {
        "name": "dataset_context_menu",
        "signature": "object,QPoint",
        "file": "ModanWidgets.py"
      },
      {
        "name": "analysis_context_menu",
        "signature": "object,QPoint",
        "file": "ModanWidgets.py"
      },
      {
        "name": "object_selected",
        "signature": "object",
        "file": "ModanWidgets.py"
      },
      {
        "name": "objects_dropped",
        "signature": "list",
        "file": "ModanWidgets.py"
      },
      {
        "name": "object_context_menu",
        "signature": "object,QPoint",
        "file": "ModanWidgets.py"
      },
      {
        "name": "landmark_clicked",
        "signature": "int",
        "file": "ModanWidgets.py"
      },
      {
        "name": "landmark_moved",
        "signature": "int,QPointF",
        "file": "ModanWidgets.py"
      },
      {
        "name": "shape_preference_changed",
        "signature": "dict",
        "file": "shape_preference.py"
      },
      {
        "name": "dataChangedCustomSignal",
        "signature": "",
        "file": "table_view.py"
      },
      {
        "name": "analysis_progress",
        "signature": "int",
        "file": "test_analysis_dialog.py"
      },
      {
        "name": "analysis_completed",
        "signature": "object",
        "file": "test_analysis_dialog.py"
      },
      {
        "name": "analysis_failed",
        "signature": "str",
        "file": "test_analysis_dialog.py"
      }
    ]
  },
  "slots": {
    "actions": [
      {
        "class": "ModanMainWindow",
        "method": "on_action_open_db_triggered",
        "file": "Modan2.py",
        "line": 529
      },
      {
        "class": "ModanMainWindow",
        "method": "on_action_new_db_triggered",
        "file": "Modan2.py",
        "line": 532
      },
      {
        "class": "ModanMainWindow",
        "method": "on_action_save_as_triggered",
        "file": "Modan2.py",
        "line": 535
      },
      {
        "class": "ModanMainWindow",
        "method": "on_action_edit_preferences_triggered",
        "file": "Modan2.py",
        "line": 745
      },
      {
        "class": "ModanMainWindow",
        "method": "on_action_exit_triggered",
        "file": "Modan2.py",
        "line": 757
      },
      {
        "class": "ModanMainWindow",
        "method": "on_action_about_triggered",
        "file": "Modan2.py",
        "line": 780
      },
      {
        "class": "ModanMainWindow",
        "method": "on_action_analyze_dataset_triggered",
        "file": "Modan2.py",
        "line": 784
      },
      {
        "class": "ModanMainWindow",
        "method": "on_action_cell_selection_triggered",
        "file": "Modan2.py",
        "line": 1012
      },
      {
        "class": "ModanMainWindow",
        "method": "on_action_row_selection_triggered",
        "file": "Modan2.py",
        "line": 1016
      },
      {
        "class": "ModanMainWindow",
        "method": "on_action_add_variable_triggered",
        "file": "Modan2.py",
        "line": 1064
      },
      {
        "class": "ModanMainWindow",
        "method": "on_action_delete_object_triggered",
        "file": "Modan2.py",
        "line": 1088
      },
      {
        "class": "ModanMainWindow",
        "method": "on_action_delete_analysis_triggered",
        "file": "Modan2.py",
        "line": 1151
      },
      {
        "class": "ModanMainWindow",
        "method": "on_action_explore_data_triggered",
        "file": "Modan2.py",
        "line": 1169
      },
      {
        "class": "ModanMainWindow",
        "method": "on_action_import_dataset_triggered",
        "file": "Modan2.py",
        "line": 1176
      },
      {
        "class": "ModanMainWindow",
        "method": "on_action_export_dataset_triggered",
        "file": "Modan2.py",
        "line": 1186
      },
      {
        "class": "ModanMainWindow",
        "method": "on_action_new_dataset_triggered",
        "file": "Modan2.py",
        "line": 1201
      },
      {
        "class": "ModanMainWindow",
        "method": "on_action_new_object_triggered",
        "file": "Modan2.py",
        "line": 1289
      }
    ],
    "ui_handlers": [
      {
        "class": "ModanMainWindow",
        "method": "btnAnalysisDetail_clicked",
        "file": "Modan2.py",
        "line": 1027
      },
      {
        "class": "ModanMainWindow",
        "method": "btnSaveAnalysis_clicked",
        "file": "Modan2.py",
        "line": 1035
      },
      {
        "class": "ModanMainWindow",
        "method": "btnDataExploration_clicked",
        "file": "Modan2.py",
        "line": 1039
      },
      {
        "class": "ModanMainWindow",
        "method": "on_btnSaveChanges_clicked",
        "file": "Modan2.py",
        "line": 1077
      },
      {
        "class": "ModanMainWindow",
        "method": "on_treeView_clicked",
        "file": "Modan2.py",
        "line": 1240
      },
      {
        "class": "ModanMainWindow",
        "method": "on_object_data_changed",
        "file": "Modan2.py",
        "line": 1521
      },
      {
        "class": "ModanMainWindow",
        "method": "on_dataset_selection_changed",
        "file": "Modan2.py",
        "line": 1718
      },
      {
        "class": "ModanMainWindow",
        "method": "on_object_selection_changed",
        "file": "Modan2.py",
        "line": 1856
      },
      {
        "class": "DatasetTreeWidget",
        "method": "_on_selection_changed",
        "file": "ModanWidgets.py",
        "line": 168
      },
      {
        "class": "DatasetTreeWidget",
        "method": "_on_item_double_clicked",
        "file": "ModanWidgets.py",
        "line": 203
      },
      {
        "class": "ObjectTableWidget",
        "method": "_on_selection_changed",
        "file": "ModanWidgets.py",
        "line": 439
      },
      {
        "class": "ObjectTableWidget",
        "method": "_on_cell_double_clicked",
        "file": "ModanWidgets.py",
        "line": 457
      },
      {
        "class": "LandmarkViewer2D",
        "method": "_on_selection_changed",
        "file": "ModanWidgets.py",
        "line": 744
      },
      {
        "class": "NewAnalysisDialog",
        "method": "edtAnalysisName_changed",
        "file": "analysis_dialog.py",
        "line": 164
      },
      {
        "class": "NewAnalysisDialog",
        "method": "btnOK_clicked",
        "file": "analysis_dialog.py",
        "line": 181
      },
      {
        "class": "NewAnalysisDialog",
        "method": "btnCancel_clicked",
        "file": "analysis_dialog.py",
        "line": 235
      },
      {
        "class": "CalibrationDialog",
        "method": "btnOK_clicked",
        "file": "calibration_dialog.py",
        "line": 104
      },
      {
        "class": "CalibrationDialog",
        "method": "btnCancel_clicked",
        "file": "calibration_dialog.py",
        "line": 113
      },
      {
        "class": "DatasetAnalysisDialog",
        "method": "on_analysis_type_changed",
        "file": "dataset_analysis_dialog.py",
        "line": 461
      },
      {
        "class": "DatasetAnalysisDialog",
        "method": "chart_options_clicked",
        "file": "dataset_analysis_dialog.py",
        "line": 494
      },
      {
        "class": "DatasetAnalysisDialog",
        "method": "on_chart_dim_changed",
        "file": "dataset_analysis_dialog.py",
        "line": 505
      },
      {
        "class": "DatasetAnalysisDialog",
        "method": "propertyname_changed",
        "file": "dataset_analysis_dialog.py",
        "line": 574
      },
      {
        "class": "DatasetAnalysisDialog",
        "method": "axis_changed",
        "file": "dataset_analysis_dialog.py",
        "line": 591
      },
      {
        "class": "DatasetAnalysisDialog",
        "method": "flip_axis_changed",
        "file": "dataset_analysis_dialog.py",
        "line": 595
      },
      {
        "class": "DatasetAnalysisDialog",
        "method": "on_btnSuperimpose_clicked",
        "file": "dataset_analysis_dialog.py",
        "line": 599
      },
      {
        "class": "DatasetAnalysisDialog",
        "method": "on_btnAnalyze_clicked",
        "file": "dataset_analysis_dialog.py",
        "line": 603
      },
      {
        "class": "DatasetAnalysisDialog",
        "method": "on_btnSaveResults_clicked",
        "file": "dataset_analysis_dialog.py",
        "line": 612
      },
      {
        "class": "DatasetAnalysisDialog",
        "method": "show_index_state_changed",
        "file": "dataset_analysis_dialog.py",
        "line": 705
      },
      {
        "class": "DatasetAnalysisDialog",
        "method": "show_average_state_changed",
        "file": "dataset_analysis_dialog.py",
        "line": 714
      },
      {
        "class": "DatasetAnalysisDialog",
        "method": "auto_rotate_state_changed",
        "file": "dataset_analysis_dialog.py",
        "line": 723
      },
      {
        "class": "DatasetAnalysisDialog",
        "method": "show_wireframe_state_changed",
        "file": "dataset_analysis_dialog.py",
        "line": 733
      },
      {
        "class": "DatasetAnalysisDialog",
        "method": "show_baseline_state_changed",
        "file": "dataset_analysis_dialog.py",
        "line": 742
      },
      {
        "class": "DatasetAnalysisDialog",
        "method": "on_btn_analysis_clicked",
        "file": "dataset_analysis_dialog.py",
        "line": 759
      },
      {
        "class": "DatasetAnalysisDialog",
        "method": "on_mouse_clicked",
        "file": "dataset_analysis_dialog.py",
        "line": 1137
      },
      {
        "class": "DatasetAnalysisDialog",
        "method": "on_scatter_item_clicked",
        "file": "dataset_analysis_dialog.py",
        "line": 1153
      },
      {
        "class": "DatasetAnalysisDialog",
        "method": "on_object_selection_changed",
        "file": "dataset_analysis_dialog.py",
        "line": 1310
      },
      {
        "class": "DataExplorationDialog",
        "method": "comboSelectGroup_changed",
        "file": "data_exploration_dialog.py",
        "line": 580
      },
      {
        "class": "DataExplorationDialog",
        "method": "comboRegressionBy_changed",
        "file": "data_exploration_dialog.py",
        "line": 592
      },
      {
        "class": "DataExplorationDialog",
        "method": "comboRegressionBasedOn_changed",
        "file": "data_exploration_dialog.py",
        "line": 608
      },
      {
        "class": "DataExplorationDialog",
        "method": "cbxShapeGrid_state_changed",
        "file": "data_exploration_dialog.py",
        "line": 615
      },
      {
        "class": "DataExplorationDialog",
        "method": "on_btnArrowColor_clicked",
        "file": "data_exploration_dialog.py",
        "line": 721
      },
      {
        "class": "DataExplorationDialog",
        "method": "shape_grid_preference_changed",
        "file": "data_exploration_dialog.py",
        "line": 731
      },
      {
        "class": "DataExplorationDialog",
        "method": "shape_preference_button_clicked",
        "file": "data_exploration_dialog.py",
        "line": 753
      },
      {
        "class": "DataExplorationDialog",
        "method": "record_animation_changed",
        "file": "data_exploration_dialog.py",
        "line": 764
      },
      {
        "class": "DataExplorationDialog",
        "method": "on_chart_dim_changed",
        "file": "data_exploration_dialog.py",
        "line": 957
      },
      {
        "class": "DataExplorationDialog",
        "method": "comboVisualizationMethod_changed",
        "file": "data_exploration_dialog.py",
        "line": 999
      },
      {
        "class": "DataExplorationDialog",
        "method": "arrow_preference_changed",
        "file": "data_exploration_dialog.py",
        "line": 1198
      },
      {
        "class": "DataExplorationDialog",
        "method": "shape_preference_changed",
        "file": "data_exploration_dialog.py",
        "line": 1203
      },
      {
        "class": "DataExplorationDialog",
        "method": "shape_button_clicked",
        "file": "data_exploration_dialog.py",
        "line": 1300
      },
      {
        "class": "DataExplorationDialog",
        "method": "axis_changed",
        "file": "data_exploration_dialog.py",
        "line": 1316
      },
      {
        "class": "DataExplorationDialog",
        "method": "flip_axis_changed",
        "file": "data_exploration_dialog.py",
        "line": 1323
      },
      {
        "class": "DataExplorationDialog",
        "method": "comboGroupBy_changed",
        "file": "data_exploration_dialog.py",
        "line": 1546
      },
      {
        "class": "DataExplorationDialog",
        "method": "comboShapeview_changed",
        "file": "data_exploration_dialog.py",
        "line": 1558
      },
      {
        "class": "ExportDatasetDialog",
        "method": "on_rbProcrustes_clicked",
        "file": "export_dialog.py",
        "line": 210
      },
      {
        "class": "ExportDatasetDialog",
        "method": "on_rbBookstein_clicked",
        "file": "export_dialog.py",
        "line": 214
      },
      {
        "class": "ExportDatasetDialog",
        "method": "on_rbRFTRA_clicked",
        "file": "export_dialog.py",
        "line": 218
      },
      {
        "class": "ExportDatasetDialog",
        "method": "on_rbNone_clicked",
        "file": "export_dialog.py",
        "line": 222
      },
      {
        "class": "ExportDatasetDialog",
        "method": "on_rbTPS_clicked",
        "file": "export_dialog.py",
        "line": 226
      },
      {
        "class": "ExportDatasetDialog",
        "method": "on_rbNTS_clicked",
        "file": "export_dialog.py",
        "line": 230
      },
      {
        "class": "ExportDatasetDialog",
        "method": "on_rbX1Y1_clicked",
        "file": "export_dialog.py",
        "line": 234
      },
      {
        "class": "ExportDatasetDialog",
        "method": "on_rbMorphologika_clicked",
        "file": "export_dialog.py",
        "line": 238
      },
      {
        "class": "ExportDatasetDialog",
        "method": "on_rbJSONZip_clicked",
        "file": "export_dialog.py",
        "line": 242
      },
      {
        "class": "ImportDatasetDialog",
        "method": "file_type_changed",
        "file": "import_dialog.py",
        "line": 283
      },
      {
        "class": "ObjectDialog",
        "method": "btnAddFile_clicked",
        "file": "object_dialog.py",
        "line": 407
      },
      {
        "class": "ObjectDialog",
        "method": "btnAddMissing_clicked",
        "file": "object_dialog.py",
        "line": 475
      },
      {
        "class": "ObjectDialog",
        "method": "show_index_state_changed",
        "file": "object_dialog.py",
        "line": 508
      },
      {
        "class": "ObjectDialog",
        "method": "show_model_state_changed",
        "file": "object_dialog.py",
        "line": 512
      },
      {
        "class": "ObjectDialog",
        "method": "show_baseline_state_changed",
        "file": "object_dialog.py",
        "line": 516
      },
      {
        "class": "ObjectDialog",
        "method": "auto_rotate_state_changed",
        "file": "object_dialog.py",
        "line": 520
      },
      {
        "class": "ObjectDialog",
        "method": "show_wireframe_state_changed",
        "file": "object_dialog.py",
        "line": 523
      },
      {
        "class": "ObjectDialog",
        "method": "show_polygon_state_changed",
        "file": "object_dialog.py",
        "line": 537
      },
      {
        "class": "ObjectDialog",
        "method": "cbxUseOriginal_state_changed",
        "file": "object_dialog.py",
        "line": 541
      },
      {
        "class": "ObjectDialog",
        "method": "btnLandmark_clicked",
        "file": "object_dialog.py",
        "line": 556
      },
      {
        "class": "ObjectDialog",
        "method": "btnCalibration_clicked",
        "file": "object_dialog.py",
        "line": 569
      },
      {
        "class": "ObjectDialog",
        "method": "btnWireframe_clicked",
        "file": "object_dialog.py",
        "line": 594
      },
      {
        "class": "ObjectDialog",
        "method": "x_changed",
        "file": "object_dialog.py",
        "line": 882
      },
      {
        "class": "ObjectDialog",
        "method": "btnAddInput_clicked",
        "file": "object_dialog.py",
        "line": 975
      },
      {
        "class": "ObjectDialog",
        "method": "btnUpdateInput_clicked",
        "file": "object_dialog.py",
        "line": 979
      },
      {
        "class": "ObjectDialog",
        "method": "btnDeleteInput_clicked",
        "file": "object_dialog.py",
        "line": 1012
      },
      {
        "class": "ObjectDialog",
        "method": "on_landmark_cell_changed",
        "file": "object_dialog.py",
        "line": 1112
      },
      {
        "class": "PreferencesDialog",
        "method": "on_rbRememberGeometryYes_clicked",
        "file": "preferences_dialog.py",
        "line": 455
      },
      {
        "class": "PreferencesDialog",
        "method": "on_rbRememberGeometryNo_clicked",
        "file": "preferences_dialog.py",
        "line": 459
      },
      {
        "class": "PreferencesDialog",
        "method": "on_rbToolbarIconLarge_clicked",
        "file": "preferences_dialog.py",
        "line": 464
      },
      {
        "class": "PreferencesDialog",
        "method": "on_rbToolbarIconSmall_clicked",
        "file": "preferences_dialog.py",
        "line": 472
      },
      {
        "class": "PreferencesDialog",
        "method": "on_rbToolbarIconMedium_clicked",
        "file": "preferences_dialog.py",
        "line": 480
      },
      {
        "class": "PreferencesDialog",
        "method": "on_rbPlotLarge_clicked",
        "file": "preferences_dialog.py",
        "line": 489
      },
      {
        "class": "PreferencesDialog",
        "method": "on_rbPlotMedium_clicked",
        "file": "preferences_dialog.py",
        "line": 493
      },
      {
        "class": "PreferencesDialog",
        "method": "on_rbPlotSmall_clicked",
        "file": "preferences_dialog.py",
        "line": 497
      },
      {
        "class": "PreferencesDialog",
        "method": "on_btnResetMarkers_clicked",
        "file": "preferences_dialog.py",
        "line": 501
      },
      {
        "class": "PreferencesDialog",
        "method": "on_btnResetPastel_clicked",
        "file": "preferences_dialog.py",
        "line": 507
      },
      {
        "class": "PreferencesDialog",
        "method": "on_btnResetVivid_clicked",
        "file": "preferences_dialog.py",
        "line": 514
      },
      {
        "class": "PreferencesDialog",
        "method": "on_lblColor_clicked",
        "file": "preferences_dialog.py",
        "line": 521
      },
      {
        "class": "PreferencesDialog",
        "method": "on_lblLmColor_clicked",
        "file": "preferences_dialog.py",
        "line": 558
      },
      {
        "class": "PreferencesDialog",
        "method": "on_lblWireframeColor_clicked",
        "file": "preferences_dialog.py",
        "line": 588
      },
      {
        "class": "PreferencesDialog",
        "method": "on_lblIndexColor_clicked",
        "file": "preferences_dialog.py",
        "line": 616
      },
      {
        "class": "PreferencesDialog",
        "method": "on_lblBgcolor_clicked",
        "file": "preferences_dialog.py",
        "line": 633
      },
      {
        "class": "TestAnalysisInfoWidgetTabManagement",
        "method": "test_tab_changed_signal",
        "file": "test_analysis_info_widget.py",
        "line": 87
      },
      {
        "class": "TestModelRoles",
        "method": "test_appendrows_preserves_changed_flag_default",
        "file": "test_landmark_count_display.py",
        "line": 48
      },
      {
        "class": "TestDelegate",
        "method": "test_size_hint_unchanged_without_missing",
        "file": "test_landmark_count_display.py",
        "line": 97
      },
      {
        "class": "TestShapePreferenceSignals",
        "method": "test_has_shape_preference_changed_signal",
        "file": "test_shape_preference.py",
        "line": 375
      },
      {
        "class": "AnalysisInfoWidget",
        "method": "on_tab_changed",
        "file": "analysis_info.py",
        "line": 174
      },
      {
        "class": "AnalysisInfoWidget",
        "method": "comboPcaGroupBy_changed",
        "file": "analysis_info.py",
        "line": 185
      },
      {
        "class": "AnalysisInfoWidget",
        "method": "comboCvaGroupBy_changed",
        "file": "analysis_info.py",
        "line": 190
      },
      {
        "class": "AnalysisInfoWidget",
        "method": "comboManovaGroupBy_changed",
        "file": "analysis_info.py",
        "line": 195
      },
      {
        "class": "ShapePreference",
        "method": "on_btnLMColor_clicked",
        "file": "shape_preference.py",
        "line": 142
      },
      {
        "class": "ShapePreference",
        "method": "on_btnEdgeColor_clicked",
        "file": "shape_preference.py",
        "line": 152
      },
      {
        "class": "ShapePreference",
        "method": "on_btnFaceColor_clicked",
        "file": "shape_preference.py",
        "line": 162
      },
      {
        "class": "ShapePreference",
        "method": "emit_changed_signal",
        "file": "shape_preference.py",
        "line": 177
      },
      {
        "class": "ShapePreference",
        "method": "btnColor_clicked",
        "file": "shape_preference.py",
        "line": 232
      }
    ]
  }
}